[{"line":2,"elements":[{"start_timestamp":"2024-06-27T07:50:39.294Z","line":4,"name":"","description":"","id":";","type":"scenario","keyword":"Scenario","steps":[{"result":{"duration":24327184500,"status":"passed"},"line":6,"name":"kullanici \"https://www.hepsiburada.com/\" adresine cep telefonu uzerinden gider","match":{"arguments":[{"val":"\"https://www.hepsiburada.com/\"","offset":10}],"location":"stepdefinitions.browserStepDefinitions.kullanici_hepsiburada_adresine_cep_telefonu_uzerinden_gider(java.lang.String)"},"keyword":"* "}],"tags":[{"name":"@browser"}]}],"name":"","description":"","id":"","keyword":"Feature","uri":"file:src/test/resources/Features/browser.feature","tags":[{"name":"@browser","type":"Tag","location":{"line":1,"column":1}}]}]